git_web_url/__init__.py
git_web_url/_version.py
git_web_url/api.py
git_web_url/cli.py
git_web_url/exc.py
git_web_url/find_repo_url.py
git_web_url/find_web_url.py
git_web_url/parser.py
git_web_url/paths.py
git_web_url/utils.py
git_web_url/vendor/__init__.py
git_web_url/vendor/git_cli.py
git_web_url/vendor/pytest_cov_helper.py
git_web_url-1.0.1.dist-info/AUTHORS.rst
git_web_url-1.0.1.dist-info/LICENSE.txt
git_web_url-1.0.1.dist-info/METADATA
git_web_url-1.0.1.dist-info/WHEEL
git_web_url-1.0.1.dist-info/entry_points.txt
git_web_url-1.0.1.dist-info/RECORD
